[
  {
    "ulid": "01FQFG9EJB2ZNCCGA3W92QF32N",
    "uuid": "7da4bce0-d82e-4ca7-97f4-bc8166b32d5d",
    "scientific_name": "alpha-bulnesene",
    "common_names": [
      "a-bulnesene"
    ],
    "category": "terpene",
    "cas_rn": "3691-11-0"
  },
  {
    "ulid": "01FQFG9EJB2ZNCCGA3W92QF32R",
    "uuid": "8d7fb342-db04-4055-9466-546cad98e2dc",
    "scientific_name": "alpha-maaliene",
    "common_names": [
      "a-maaliene"
    ],
    "category": "terpene",
    "cas_rn": "489-28-1"
  },
  {
    "ulid": "018NY6XC00LMPS11DW5VC5ZDF6",
    "uuid": "dc7e4749-b937-4bbd-ae2e-60e7cefa25ce",
    "scientific_name": "alpha-ocimene",
    "common_names": [
      "a-ocimene"
    ],
    "category": "terpene",
    "cas_rn": "3338-55-4"
  },
  {
    "ulid": "01FQFG9EJC2Z0EFM33WDMPDEVA",
    "uuid": "8efb7214-e82d-402c-aeac-a2cd970bf3b9",
    "scientific_name": "alpha-phellandrene",
    "common_names": [
      "a-phellandrene"
    ],
    "category": "terpene",
    "cas_rn": "99-83-2"
  },
  {
    "ulid": "018NY6XC00LMCG3GPPN8QDAGAQ",
    "uuid": "0a0a945d-d497-46a6-9f94-1bc84c89b176",
    "scientific_name": "alpha-pinene",
    "common_names": [
      "a-pinene"
    ],
    "category": "terpene",
    "cas_rn": "80-56-8"
  },
  {
    "ulid": "01FQFG9EJB2ZNCCGA3W92QF33G",
    "uuid": "6b67194c-726c-4995-bd99-7346f984fb67",
    "scientific_name": "alpha-santalene",
    "common_names": [
      "a-santalene"
    ],
    "category": "terpene",
    "cas_rn": "512-61-8"
  },
  {
    "ulid": "01FQFG9EJB2ZNCCGA3W92QF32W",
    "uuid": "fe599d14-eece-40c9-b2aa-659e04f41e54",
    "scientific_name": "alpha-terpinene",
    "common_names": [
      "a-terpinene"
    ],
    "category": "terpene",
    "cas_rn": "99-86-5"
  },
  {
    "ulid": "01FQFG9EJB2ZNCCGA3W92QF32V",
    "uuid": "453bd446-78c3-48f4-9317-bc24dc55b054",
    "scientific_name": "beta-maaliene",
    "common_names": [
      "b-maaliene"
    ],
    "category": "terpene",
    "cas_rn": "489-29-2"
  },
  {
    "ulid": "01FQFG9EJB2ZNCCGA3W92QF32Y",
    "uuid": "a76db256-59f8-4d59-9837-5a1ae914c8d4",
    "scientific_name": "beta-ocimene",
    "common_names": [
      "b-ocimene"
    ],
    "category": "terpene",
    "cas_rn": "13877-91-3"
  },
  {
    "ulid": "01FQFG9EJB2ZNCCGA3W92QF32X",
    "uuid": "d20d8453-e64b-4a6f-adb6-5444e235857e",
    "scientific_name": "beta-phellandrene",
    "common_names": [
      "b-phellandrene"
    ],
    "category": "terpene",
    "cas_rn": "55-10-2"
  },
  {
    "ulid": "018NY6XC00LM733KQWC064C0X8",
    "uuid": "36a0bda9-150a-43ed-9c0b-6e4130f6c32b",
    "scientific_name": "beta-pinene",
    "common_names": [
      "b-pinene"
    ],
    "category": "terpene",
    "cas_rn": "127-91-3"
  },
  {
    "ulid": "018NY6XC00LMKW46MMS466FK9F",
    "uuid": "6baa893e-1c2c-44e6-bd03-ac80d864108b",
    "scientific_name": "bisabolene",
    "common_names": [
      "bisabolene"
    ],
    "category": "terpene",
    "cas_rn": "17627-44-0"
  },
  {
    "ulid": "018NY6XC00LMM3YXXC8Y2W9T8N",
    "uuid": "b3bd1b60-bdc5-4754-8e19-ef907e76c5ea",
    "scientific_name": "bisabolol",
    "common_names": [
      "bisabolol"
    ],
    "category": "terpene",
    "cas_rn": "515-69-5"
  },
  {
    "ulid": "018NY6XC00LM5RP8VV8TQAJ92A",
    "uuid": "814a0477-c6f0-4df4-aea4-070a0ddeb9d5",
    "scientific_name": "camphene",
    "common_names": [
      "camphene"
    ],
    "category": "terpene",
    "cas_rn": "79-92-5"
  },
  {
    "ulid": "018NY6XC00LMKMYDTB18499106",
    "uuid": "29823bdd-c106-4134-be5a-54b5b27cdca3",
    "scientific_name": "carene",
    "common_names": [
      "carene"
    ],
    "category": "terpene",
    "cas_rn": "13466-78-9"
  },
  {
    "ulid": "01FQFG9EJB2ZNCCGA3W92QF334",
    "uuid": "180f6a54-1bd3-49ee-acc9-8206fdbbef3f",
    "scientific_name": "caryophyllene",
    "common_names": [
      "caryophyllene"
    ],
    "category": "terpene",
    "cas_rn": "87-44-5"
  },
  {
    "ulid": "018NY6XC002GH0MJ4KFFBE79WN",
    "uuid": "25bbd708-d059-4f3d-8fce-db28b066d174",
    "scientific_name": "caryophyllene oxide",
    "common_names": [
      "caryophyllene oxide"
    ],
    "category": "terpene",
    "cas_rn": "1139-30-6"
  },
  {
    "ulid": "01FQFG9EJC2Z0EFM33WDMPDEVQ",
    "uuid": "80c77935-0d13-4d9f-ad33-f91888d8d5a8",
    "scientific_name": "cedrol",
    "common_names": [
      "cedrol"
    ],
    "category": "terpene",
    "cas_rn": "77-53-2"
  },
  {
    "ulid": "01FQFG9EJB2ZNCCGA3W92QF34E",
    "uuid": "69e00664-1b5f-4216-b3af-e280596a7f28",
    "scientific_name": "cis-alpha-bergamotene",
    "common_names": [
      "cis-a-bergamotene"
    ],
    "category": "terpene",
    "cas_rn": "18252-46-5"
  },
  {
    "ulid": "01FQFG9EJB2ZNCCGA3W92QF34W",
    "uuid": "ac81b53a-476d-44c8-8ce9-5e3ae506aa36",
    "scientific_name": "cis-carveol",
    "common_names": [
      "cis-carveol"
    ],
    "category": "terpene",
    "cas_rn": "1197-06-4"
  },
  {
    "ulid": "018NY6XC004NQKFWGHH2V2HPDT",
    "uuid": "33266eec-0953-43ca-8fa3-e917841c9e51",
    "scientific_name": "cis-nerolidol",
    "common_names": [
      "cis-nerolidol"
    ],
    "category": "terpene",
    "cas_rn": "3790-78-1"
  },
  {
    "ulid": "01FQFG9EJB2ZNCCGA3W92QF33X",
    "uuid": "bde05067-aab1-4463-9a40-221cbdfee278",
    "scientific_name": "citronellol",
    "common_names": [
      "citronellol"
    ],
    "category": "terpene",
    "cas_rn": "106-22-9"
  },
  {
    "ulid": "018NY6XC00LM2E59R89FKZEVY8",
    "uuid": "e5007906-9824-4024-9ac4-a86d57c0c4f6",
    "scientific_name": "eucalyptol",
    "common_names": [
      "eucalyptol"
    ],
    "category": "terpene",
    "cas_rn": "470-82-6"
  },
  {
    "ulid": "01FQFG9EJB2ZNCCGA3W92QF33Z",
    "uuid": "1301124c-6b16-477f-9ea8-201b0924651c",
    "scientific_name": "eudesmol",
    "common_names": [
      "eudesmol"
    ],
    "category": "terpene",
    "cas_rn": "473-15-4"
  },
  {
    "ulid": "018NY6XC00LMAX6W83M65P4RDF",
    "uuid": "66b7a0e3-c92b-4c03-9992-400be51c40f9",
    "scientific_name": "farnesene",
    "common_names": [
      "farnesene"
    ],
    "category": "terpene",
    "cas_rn": "502-61-4"
  },
  {
    "ulid": "018NY6XC00LM8TPPW71WHPJHS9",
    "uuid": "4804aed1-2366-424c-897e-81e8a376d2c4",
    "scientific_name": "fenchol",
    "common_names": [
      "fenchol"
    ],
    "category": "terpene",
    "cas_rn": "1632-73-1"
  },
  {
    "ulid": "01FQFG9EJB2ZNCCGA3W92QF343",
    "uuid": "b582b25d-7b0e-4ca5-b2a5-380887dbd03c",
    "scientific_name": "fenchone",
    "common_names": [
      "fenchone"
    ],
    "category": "terpene",
    "cas_rn": "1195-79-5"
  },
  {
    "ulid": "01FQFG9EJB2ZNCCGA3W92QF341",
    "uuid": "2b180cc4-65b7-442b-a7bd-9a96191f7899",
    "scientific_name": "gamma-guaiene",
    "common_names": [
      "g-guaiene"
    ],
    "category": "terpene",
    "cas_rn": "3691-12-1"
  },
  {
    "ulid": "018NY6XC00QJQVPK47XK0HMYGT",
    "uuid": "becbf9d0-fbde-4ce9-aadf-4feac8fd31de",
    "scientific_name": "gamma-terpinene",
    "common_names": [
      "g-terpinene"
    ],
    "category": "terpene",
    "cas_rn": "99-85-4"
  },
  {
    "ulid": "018NY6XC00LM1FFPX84N11Y960",
    "uuid": "098424b8-97ae-44e6-979f-ce80c53833a1",
    "scientific_name": "geraniol",
    "common_names": [
      "geraniol"
    ],
    "category": "terpene",
    "cas_rn": "106-24-1"
  },
  {
    "ulid": "018NY6XC00LMQQDFGS8QBAKJ3J",
    "uuid": "5555502a-7dce-4aed-b8b6-7270922b0039",
    "scientific_name": "guaiol",
    "common_names": [
      "guaiol"
    ],
    "category": "terpene",
    "cas_rn": "489-86-1"
  },
  {
    "ulid": "01FQFG9EJB2ZNCCGA3W92QF347",
    "uuid": "4be468b0-93d0-4f13-b493-ffbc2482d97e",
    "scientific_name": "himachalene",
    "common_names": [
      "himachalene"
    ],
    "category": "terpene",
    "cas_rn": "1461-03-06"
  },
  {
    "ulid": "018NY6XC00LMQF9D59E5T0QA0A",
    "uuid": "8c95be83-91b0-4308-88d5-56f667234fb9",
    "scientific_name": "humulene",
    "common_names": [
      "humulene"
    ],
    "category": "terpene",
    "cas_rn": "6753-98-6"
  },
  {
    "ulid": "01FQFG9EJC2Z0EFM33WDMPDEVR",
    "uuid": "995d66bd-9fc3-4ffa-9ef8-c726752c9e54",
    "scientific_name": "humulene oxide ii",
    "common_names": [
      "humulene oxide"
    ],
    "category": "terpene",
    "cas_rn": "19888-34-7"
  },
  {
    "ulid": "018NY6XC00LMFG9ZMJNQJ9AE5F",
    "uuid": "0435c46d-bd0b-4ba9-bae9-1fb806c41592",
    "scientific_name": "isopulegol",
    "common_names": [
      "isopulegol"
    ],
    "category": "terpene",
    "cas_rn": "89-79-2"
  },
  {
    "ulid": "018NY6XC00LM6J8FQHSXARDVMZ",
    "uuid": "b5c99df0-24f6-44d3-9bee-209c2fc7552c",
    "scientific_name": "limonene",
    "common_names": [
      "limonene"
    ],
    "category": "terpene",
    "cas_rn": "5989-27-5"
  },
  {
    "ulid": "018NY6XC00LMK42ZVHZYKNQ1P0",
    "uuid": "eab8f974-e3f0-45d0-9947-0d91f5469791",
    "scientific_name": "linalool",
    "common_names": [
      "linalool"
    ],
    "category": "terpene",
    "cas_rn": "78-70-6"
  },
  {
    "ulid": "018NY6XC00LMH4TQXDXKH97K87",
    "uuid": "e49f45d9-d652-4812-a943-9a15d35e4ffa",
    "scientific_name": "myrcene",
    "common_names": [
      "myrcene"
    ],
    "category": "terpene",
    "cas_rn": "123-35-3"
  },
  {
    "ulid": "018NY6XC00LMQW6Q8FE142912R",
    "uuid": "c41ccc2e-23e8-4944-ba4c-3f48a4468c80",
    "scientific_name": "para-cymene",
    "common_names": [
      "p-cymene"
    ],
    "category": "terpene",
    "cas_rn": "99-87-6"
  },
  {
    "ulid": "01FQFG9EJC2Z0EFM33WDMPDEVF",
    "uuid": "7083bcf4-f44a-4380-8768-ecd513c88e15",
    "scientific_name": "pseudo-valencene",
    "common_names": [
      "pseudo-valencene"
    ],
    "category": "terpene",
    "cas_rn": "58893-88-2"
  },
  {
    "ulid": "018NY6XC00LM2W05964HBRZ57R",
    "uuid": "25de2bee-23e8-4d37-95a2-56a3b8206174",
    "scientific_name": "sabinene",
    "common_names": [
      "sabinene"
    ],
    "category": "terpene",
    "cas_rn": "3387-41-5"
  },
  {
    "ulid": "01FQFG9EJB2ZNCCGA3W92QF35C",
    "uuid": "78ce0061-385e-41a1-acb3-b22845390de0",
    "scientific_name": "selinadiene",
    "common_names": [
      "selinadiene"
    ],
    "category": "terpene",
    "cas_rn": "28290-20-2"
  },
  {
    "ulid": "01FQFG9EJB2ZNCCGA3W92QF35D",
    "uuid": "b1d87826-fc8e-4a8d-a3b3-dff526bce627",
    "scientific_name": "sulcatone",
    "common_names": [
      "sulcatone"
    ],
    "category": "terpene",
    "cas_rn": "110-93-0"
  },
  {
    "ulid": "018NY6XC00LMMQ4V3VTBQ83QWW",
    "uuid": "a752aea3-21e5-43bd-973e-d96393c7a2aa",
    "scientific_name": "terpineol",
    "common_names": [
      "terpineol"
    ],
    "category": "terpene",
    "cas_rn": "98-55-5"
  },
  {
    "ulid": "018NY6XC00LMBFR51SFFGQJXRF",
    "uuid": "f5abedee-c07a-428b-ae5b-673eb27b74eb",
    "scientific_name": "terpinolene",
    "common_names": [
      "terpinolene"
    ],
    "category": "terpene",
    "cas_rn": "586-62-9"
  },
  {
    "ulid": "01FQFG9EJB2ZNCCGA3W92QF35E",
    "uuid": "5392feb4-78fe-40fd-94c2-5a7a60d300e4",
    "scientific_name": "thujene",
    "common_names": [
      "thujene"
    ],
    "category": "terpene",
    "cas_rn": "3387-41-5"
  },
  {
    "ulid": "01FQFG9EJC2Z0EFM33WDMPDEVG",
    "uuid": "f059af4d-aa94-47c9-ac16-a43ccfd2b5f9",
    "scientific_name": "thymol",
    "common_names": [
      "thymol"
    ],
    "category": "terpene",
    "cas_rn": "89-83-8"
  },
  {
    "ulid": "01FQFG9EJC2Z0EFM33WDMPDEVJ",
    "uuid": "c2dccf9d-3c75-4adc-b77e-b06ef16bb541",
    "scientific_name": "trans-2-pinanol",
    "common_names": [
      "trans-2-pinanol"
    ],
    "category": "terpene",
    "cas_rn": "4948-29-2"
  },
  {
    "ulid": "01FQFG9EJC2Z0EFM33WDMPDEVK",
    "uuid": "64dec026-e54f-4d94-8806-ab77d3ccc7ca",
    "scientific_name": "trans-alpha-bergamotene",
    "common_names": [
      "trans-a-bergamotene"
    ],
    "category": "terpene",
    "cas_rn": "13474-59-4"
  },
  {
    "ulid": "018NY6XC00LMJ3HV06KJXPR9F3",
    "uuid": "ac28c6bd-edb7-4e81-b92d-f2a714244067",
    "scientific_name": "trans-nerolidol",
    "common_names": [
      "trans-nerolidol",
      "(+)-trans-Nerolidol"
    ],
    "category": "terpene",
    "cas_rn": "40716-66-3"
  },
  {
    "ulid": "01FQFG9EJC2Z0EFM33WDMPDEV4",
    "uuid": "43e21d47-ef0b-4b44-b28e-cb5cd7fc18cd",
    "scientific_name": "trans-ocimene",
    "common_names": [
      "trans-ocimene"
    ],
    "category": "terpene",
    "cas_rn": "3779-61-1"
  },
  {
    "ulid": "018NY6XC00HKGZD7C613RNE0Z0",
    "uuid": "4dbbb9a4-8a39-4fe2-a02f-ab05ada243d1",
    "scientific_name": "7-hydroxymitragynine",
    "common_names": [
      "7-hydroxymitragynine"
    ],
    "category": "terpene",
    "cas_rn": null
  },
  {
    "ulid": "018NY6XC00LM0Q5E8PYHY9WQ57",
    "uuid": "1ad1d77b-bb5e-44aa-b62e-7eef962a8118",
    "scientific_name": "beta-myrcene",
    "common_names": [
      "beta-myrcene"
    ],
    "category": "terpene",
    "cas_rn": null
  },
  {
    "ulid": "018NY6XC00LM3APZQTH7XYAZSC",
    "uuid": "543fdb6b-d6f8-43ca-9067-d23b51b88178",
    "scientific_name": "menthol",
    "common_names": [
      "menthol"
    ],
    "category": "terpene",
    "cas_rn": null
  },
  {
    "ulid": "018NY6XC00LM4F7B8D750PBBVF",
    "uuid": "e250cf58-5fbf-4aee-9e48-2dae70890cb6",
    "scientific_name": "cineole",
    "common_names": [
      "cineole"
    ],
    "category": "terpene",
    "cas_rn": null
  },
  {
    "ulid": "018NY6XC00LM5P16C5VW3F7450",
    "uuid": "8044ad3c-b84d-4ed8-bbec-17bbc1373969",
    "scientific_name": "terpinene",
    "common_names": [
      "terpinene"
    ],
    "category": "terpene",
    "cas_rn": null
  },
  {
    "ulid": "018NY6XC00LM66ZHJD25GNSFRN",
    "uuid": "85cd280d-40d0-4589-b0f2-805dc121a205",
    "scientific_name": "camphor",
    "common_names": [
      "camphor"
    ],
    "category": "terpene",
    "cas_rn": null
  },
  {
    "ulid": "018NY6XC00LM7R6CF7AEZ3MN34",
    "uuid": "5a9a29d0-41f2-46e6-9273-a195f9387f5a",
    "scientific_name": "geranyl acetate",
    "common_names": [
      "geranyl acetate"
    ],
    "category": "terpene",
    "cas_rn": null
  },
  {
    "ulid": "018NY6XC00LM86MPJP7VHVDR00",
    "uuid": "989047b2-e3d7-4858-852b-4f7d92d8d09a",
    "scientific_name": "cedrene",
    "common_names": [
      "cedrene"
    ],
    "category": "terpene",
    "cas_rn": null
  },
  {
    "ulid": "018NY6XC00LM9QSV7PQDRB1VEY",
    "uuid": "de715f04-6790-4953-a343-e91c28ba66de",
    "scientific_name": "beta-caryophyllene",
    "common_names": [
      "beta-caryophyllene"
    ],
    "category": "terpene",
    "cas_rn": null
  },
  {
    "ulid": "018NY6XC00LMBGSXW5YQR4NYPZ",
    "uuid": "f199ff22-600c-48d7-be89-eb48eb0589ee",
    "scientific_name": "phellandrene",
    "common_names": [
      "phellandrene"
    ],
    "category": "terpene",
    "cas_rn": null
  },
  {
    "ulid": "018NY6XC00LMCNR9XRJQXE0MFR",
    "uuid": "c835d234-d6ea-4944-ac28-3ad146150c7c",
    "scientific_name": "phytol",
    "common_names": [
      "phytol"
    ],
    "category": "terpene",
    "cas_rn": null
  },
  {
    "ulid": "018NY6XC00LMHBS2P1D4M5WZ6Q",
    "uuid": "f63800bd-6a2f-413c-86ce-49a0f76916f8",
    "scientific_name": "elemene",
    "common_names": [
      "elemene"
    ],
    "category": "terpene",
    "cas_rn": null
  },
  {
    "ulid": "018NY6XC00LMJ8HWPTK92118TJ",
    "uuid": "792dcc91-6d36-471d-a2da-aed531af647a",
    "scientific_name": "delta 3 carene",
    "common_names": [
      "delta 3 carene"
    ],
    "category": "terpene",
    "cas_rn": null
  },
  {
    "ulid": "018NY6XC00LMJX17TGNPYAX2E6",
    "uuid": "1bce6e17-1d27-4624-8c1d-e808966672d6",
    "scientific_name": "pinene",
    "common_names": [
      "pinene"
    ],
    "category": "terpene",
    "cas_rn": null
  },
  {
    "ulid": "018NY6XC00LMPV2GSPRBZXC08Y",
    "uuid": "0516cc77-ebde-4835-be39-60404f0c32bc",
    "scientific_name": "trans-nerolido",
    "common_names": [
      "trans-nerolido"
    ],
    "category": "terpene",
    "cas_rn": null
  },
  {
    "ulid": "018NY6XC00LMQW96F7VFGSCTYK",
    "uuid": "0f5c929b-900e-4025-865f-bcd0b53543b4",
    "scientific_name": "alpha-bisabolol",
    "common_names": [
      "alpha-bisabolol"
    ],
    "category": "terpene",
    "cas_rn": null
  },
  {
    "ulid": "018NY6XC00LMQZWHD25XN1F7BZ",
    "uuid": "62e40b4a-e302-4447-9972-3f3d98b87956",
    "scientific_name": "bergamotene",
    "common_names": [
      "bergamotene"
    ],
    "category": "terpene",
    "cas_rn": null
  },
  {
    "ulid": "018NY6XC00LMSF0HPDC29T1QH1",
    "uuid": "18083140-41c6-4ebc-9b2f-4bd175e41e1c",
    "scientific_name": "pulegone",
    "common_names": [
      "pulegone"
    ],
    "category": "terpene",
    "cas_rn": null
  },
  {
    "ulid": "018NY6XC00LMSTHMFW45MD2ECS",
    "uuid": "bcea1a77-ef04-4768-8136-f233f96e2e12",
    "scientific_name": "borneol",
    "common_names": [
      "borneol"
    ],
    "category": "terpene",
    "cas_rn": null
  },
  {
    "ulid": "018NY6XC00LMTXQC4X18WTB71J",
    "uuid": "f131a071-b9e2-4bf0-a5a8-c77de1d487b3",
    "scientific_name": "isoborneol",
    "common_names": [
      "isoborneol"
    ],
    "category": "terpene",
    "cas_rn": null
  },
  {
    "ulid": "018NY6XC00LMTYA0APDKAK3DVH",
    "uuid": "592e2195-72b5-4f10-b61e-e558449e8bd8",
    "scientific_name": "isophytol",
    "common_names": [
      "isophytol"
    ],
    "category": "terpene",
    "cas_rn": null
  },
  {
    "ulid": "018NY6XC00LMXPVBJE1ZFAXSA9",
    "uuid": "cde1bfa0-6927-40e4-b6b5-10b375d1c61a",
    "scientific_name": "valencene",
    "common_names": [
      "valencene"
    ],
    "category": "terpene",
    "cas_rn": null
  },
  {
    "ulid": "018NY6XC00LMZJ5AVZN2MWG32M",
    "uuid": "477cc52c-ea0d-4adc-aef7-3268db5e7ef0",
    "scientific_name": "aromadendrene",
    "common_names": [
      "aromadendrene"
    ],
    "category": "terpene",
    "cas_rn": null
  }
]
